pyhdb_rs/__init__.py
pyhdb_rs/_core.pyi
pyhdb_rs/_core.pypy311-pp73-aarch64-linux-gnu.so
pyhdb_rs/aio/__init__.py
pyhdb_rs/aio/_core.pyi
pyhdb_rs/dbapi.py
pyhdb_rs/py.typed
pyhdb_rs-0.3.2.dist-info/METADATA
pyhdb_rs-0.3.2.dist-info/WHEEL
pyhdb_rs.libs/libgcc_s-0bf60adc.so.1
pyhdb_rs-0.3.2.dist-info/RECORD
