Metadata-Version: 2.4
Name: pyhdb_rs
Version: 0.3.2
Classifier: Development Status :: 3 - Alpha
Classifier: Intended Audience :: Developers
Classifier: License :: OSI Approved :: Apache Software License
Classifier: License :: OSI Approved :: MIT License
Classifier: Programming Language :: Python :: 3
Classifier: Programming Language :: Python :: 3.12
Classifier: Programming Language :: Python :: 3.13
Classifier: Programming Language :: Python :: 3.14
Classifier: Programming Language :: Rust
Classifier: Topic :: Database
Classifier: Topic :: Database :: Front-Ends
Classifier: Typing :: Typed
Requires-Dist: polars>=1.0 ; extra == 'all'
Requires-Dist: pandas>=2.0 ; extra == 'all'
Requires-Dist: pyarrow>=14.0 ; extra == 'all'
Requires-Dist: pytest>=9.0 ; extra == 'benchmark'
Requires-Dist: pytest-benchmark>=5.1 ; extra == 'benchmark'
Requires-Dist: polars>=1.0 ; extra == 'benchmark'
Requires-Dist: pandas>=2.0 ; extra == 'benchmark'
Requires-Dist: pyarrow>=14.0 ; extra == 'benchmark'
Requires-Dist: maturin>=1.11,<2 ; extra == 'dev'
Requires-Dist: pytest>=9.0 ; extra == 'dev'
Requires-Dist: pytest-cov>=4.0 ; extra == 'dev'
Requires-Dist: pytest-asyncio>=1.3.0,<2 ; extra == 'dev'
Requires-Dist: pytest-benchmark>=5.1 ; extra == 'dev'
Requires-Dist: ruff>=0.5 ; extra == 'dev'
Requires-Dist: mypy>=1.10 ; extra == 'dev'
Requires-Dist: polars>=1.0 ; extra == 'dev'
Requires-Dist: pandas>=2.0 ; extra == 'dev'
Requires-Dist: pyarrow>=14.0 ; extra == 'dev'
Requires-Dist: pandas>=2.0 ; extra == 'pandas'
Requires-Dist: pyarrow>=22.0,<24 ; extra == 'pandas'
Requires-Dist: polars>=1.0 ; extra == 'polars'
Provides-Extra: all
Provides-Extra: async
Provides-Extra: benchmark
Provides-Extra: dev
Provides-Extra: pandas
Provides-Extra: polars
Summary: High-performance Python driver for SAP HANA with native Arrow support
Keywords: sap,hana,database,arrow,polars,pandas
Author-email: Andrei G <andrei.g@my.com>
License: Apache-2.0 OR MIT
Requires-Python: >=3.12
Project-URL: Bug Tracker, https://github.com/bug-ops/pyhdb-rs/issues
Project-URL: Changelog, https://github.com/bug-ops/pyhdb-rs/blob/main/CHANGELOG.md
Project-URL: Documentation, https://github.com/bug-ops/pyhdb-rs#readme
Project-URL: Homepage, https://github.com/bug-ops/pyhdb-rs
Project-URL: Repository, https://github.com/bug-ops/pyhdb-rs
